README.txt
setup.py
findmyi/__init__.py
findmyi.egg-info/PKG-INFO
findmyi.egg-info/SOURCES.txt
findmyi.egg-info/dependency_links.txt
findmyi.egg-info/requires.txt
findmyi.egg-info/top_level.txt