Metadata-Version: 1.1
Name: findmyi
Version: 0.2
Summary: A simple Python interface to Find My iPhone over the iCloud service
Home-page: https://bitbucket.org/raphaelmutschler/fmi
Author: Raphael Mutschler
Author-email: info@raphaelmutschler.de
License: UNKNOWN
Download-URL: https://bitbucket.org/raphaelmutschler/fmi/get/master.tar.gz
Keywords: find my iphone,apple,icloud
Platform: UNKNOWN
